stowrypy/__init__.py
stowrypy/client.py
stowrypy/py.typed
stowrypy-0.1.0.dist-info/WHEEL
stowrypy-0.1.0.dist-info/METADATA
stowrypy-0.1.0.dist-info/RECORD
