Metadata-Version: 2.4
Name: stowrypy
Version: 0.1.0
Summary: Python SDK for generating Stowry presigned URLs
Keywords: stowry,presigned-url,s3,object-storage
Author: Sagar Chavan
Author-email: Sagar Chavan <sagar.c.03@gmail.com>
License-Expression: MIT
Classifier: Development Status :: 4 - Beta
Classifier: Intended Audience :: Developers
Classifier: License :: OSI Approved :: MIT License
Classifier: Operating System :: OS Independent
Classifier: Programming Language :: Python :: 3
Classifier: Programming Language :: Python :: 3.10
Classifier: Programming Language :: Python :: 3.11
Classifier: Programming Language :: Python :: 3.12
Classifier: Programming Language :: Python :: 3.13
Classifier: Programming Language :: Python :: 3.14
Classifier: Topic :: Software Development :: Libraries :: Python Modules
Classifier: Typing :: Typed
Requires-Python: >=3.10
Project-URL: Homepage, https://github.com/sagarc03/stowrypy
Project-URL: Repository, https://github.com/sagarc03/stowrypy
Project-URL: Issues, https://github.com/sagarc03/stowrypy/issues
